aipip/__init__.py
aipip/cli/__init__.py
aipip/cli/run_text_generation.py
aipip/config/__init__.py
aipip/config/loader.py
aipip/config/models.py
aipip/providers/__init__.py
aipip/providers/registry.py
aipip/providers/clients/__init__.py
aipip/providers/clients/anthropic_client.py
aipip/providers/clients/google_client.py
aipip/providers/clients/openai_client.py
aipip/providers/interfaces/__init__.py
aipip/providers/interfaces/text_provider.py
aipip/services/__init__.py
aipip/services/text_generation_service.py
aipip-0.1.0.dist-info/licenses/LICENSE
aipip-0.1.0.dist-info/METADATA
aipip-0.1.0.dist-info/WHEEL
aipip-0.1.0.dist-info/top_level.txt
aipip-0.1.0.dist-info/RECORD
