Metadata-Version: 2.4
Name: aipip
Version: 0.1.0
Summary: AI Provider Interaction Platform - A flexible framework for interacting with various AI provider APIs.
Author-email: Artifig <otto@artifig.com>
License: MIT License
Project-URL: Homepage, https://github.com/ottomattas/aipip
Project-URL: Bug Tracker, https://github.com/ottomattas/aipip/issues
Classifier: License :: OSI Approved :: MIT License
Classifier: Programming Language :: Python :: 3
Classifier: Programming Language :: Python :: 3.9
Classifier: Programming Language :: Python :: 3.10
Classifier: Programming Language :: Python :: 3.11
Classifier: Programming Language :: Python :: 3.12
Classifier: Operating System :: OS Independent
Classifier: Intended Audience :: Developers
Classifier: Topic :: Scientific/Engineering :: Artificial Intelligence
Classifier: Topic :: Software Development :: Libraries :: Python Modules
Requires-Python: >=3.9
License-File: LICENSE
Requires-Dist: pydantic>=2.0
Requires-Dist: pydantic-settings>=2.0
Requires-Dist: openai>=1.0
Requires-Dist: google-generativeai>=0.5
Requires-Dist: anthropic>=0.20
Provides-Extra: dev
Requires-Dist: pytest>=7.0; extra == "dev"
Requires-Dist: python-dotenv>=1.0.0; extra == "dev"
Dynamic: license-file
